tailrec/__init__.py
tailrec/__init__.pyi
tailrec-0.1.6.dist-info/LICENSE
tailrec-0.1.6.dist-info/METADATA
tailrec-0.1.6.dist-info/WHEEL
tailrec-0.1.6.dist-info/RECORD
