Metadata-Version: 2.3
Name: tailrec
Version: 0.1.6
Summary: Execute a tail recursive function iteratively
License: MIT
Author: Christian Kreutz
Author-email: christian.kreutz.dev@stud.uni-due.de
Requires-Python: >=3.11
Classifier: License :: OSI Approved :: MIT License
Classifier: Programming Language :: Python :: 3
Classifier: Programming Language :: Python :: 3.11
Classifier: Programming Language :: Python :: 3.12
Classifier: Programming Language :: Python :: 3.13
Project-URL: Repository, https://github.com/chr3st5an/tailrec
